flask_celeryext/__init__.py
flask_celeryext/_mapping.py
flask_celeryext/app.py
flask_celeryext/ext.py
Flask_CeleryExt-0.5.0.dist-info/AUTHORS.rst
Flask_CeleryExt-0.5.0.dist-info/LICENSE
Flask_CeleryExt-0.5.0.dist-info/METADATA
Flask_CeleryExt-0.5.0.dist-info/WHEEL
Flask_CeleryExt-0.5.0.dist-info/top_level.txt
Flask_CeleryExt-0.5.0.dist-info/RECORD
