Metadata-Version: 2.1
Name: Flask-CeleryExt
Version: 0.5.0
Summary: "Flask-CeleryExt is a simple integration layer between Celery and Flask."
Home-page: https://github.com/inveniosoftware/flask-celeryext
Author: CERN
Author-email: info@inveniosoftware.org
License: BSD
Keywords: flask celery
Platform: any
Classifier: Development Status :: 5 - Production/Stable
Requires-Python: >=3.6
Provides-Extra: tests
